alphagens/__init__.py
alphagens/agent.py
alphagens/api.py
alphagens/backtest.py
alphagens/calendars.py
alphagens/cli.py
alphagens/env.py
alphagens/factor_utils.py
alphagens/frame.py
alphagens/pipeline.py
alphagens/rollings.py
alphagens/tears.py
alphagens/types.py
alphagens/cli/__init__.py
alphagens/cli/main_cli.py
alphagens/cli/texgen.py
alphagens/data/__init__.py
alphagens/data/data_portal.py
alphagens/data_source/__init__.py
alphagens/data_source/_dataapi_linux36.py
alphagens/data_source/tushare.py
alphagens/data_source/uqer.py
alphagens/edbt/__init__.py
alphagens/edbt/account.py
alphagens/edbt/algorithm.py
alphagens/edbt/broker.py
alphagens/edbt/engine.py
alphagens/edbt/strategy.py
alphagens/edbt/test.py
alphagens/edbt/model/__init__.py
alphagens/edbt/model/commission.py
alphagens/edbt/model/fee.py
alphagens/edbt/model/slippage.py
alphagens/factor/__init__.py
alphagens/factor/parser.py
alphagens/factor/preprocessing.py
alphagens/op/__init__.py
alphagens/op/functional.py
alphagens/options/__init__.py
alphagens/pipeline/__init__.py
alphagens/pipeline/pipeline.py
alphagens/pyfolio/__init__.py
alphagens/pyfolio/naive.py
alphagens/pyfolio/optimizer.py
alphagens/pyfolio/test.py
alphagens/utils/__init__.py
alphagens/utils/calendars.py
alphagens/utils/email.py
alphagens/utils/format_output.py
alphagens/utils/latex.py
alphagens/utils/metrics.py
alphagens/utils/rebalance.py
alphagens/utils/stats.py
alphagens/utils/visualization.py
alphagens/vbt/__init__.py
alphagens/vbt/backtest.py
alphagens-0.5.5.dist-info/METADATA
alphagens-0.5.5.dist-info/WHEEL
alphagens-0.5.5.dist-info/entry_points.txt
alphagens-0.5.5.dist-info/top_level.txt
alphagens-0.5.5.dist-info/RECORD
