Metadata-Version: 2.1
Name: alphagens
Version: 0.5.5
Summary: An event-driven backtesting system
Download-URL: https://github.com/nymath/alphagens/releases/tag/v1.0
Author: ny
Author-email: nymath@163.com
Project-URL: Homepage, https://github.com/nymath/alphagens
Project-URL: Documentation, https://github.com/nymath/alphagens
Project-URL: Download, https://github.com/nymath/alphagens/releases/tag/v1.0
Project-URL: Source, https://github.com/nymath/alphagens
Classifier: Development Status :: 3 - Alpha
Classifier: Programming Language :: Python :: 3
Classifier: License :: OSI Approved :: MIT License
Classifier: Operating System :: Unix
Requires-Python: >=3.9
Requires-Dist: numpy
Requires-Dist: pandas
Requires-Dist: pandas-market-calendars
Requires-Dist: joblib (>=1.2.0)
Requires-Dist: pyperclip
Requires-Dist: tushare
